libntp.py
libntp-0.1.1.dist-info/LICENSE
libntp-0.1.1.dist-info/METADATA
libntp-0.1.1.dist-info/WHEEL
libntp-0.1.1.dist-info/RECORD
