Metadata-Version: 2.1
Name: libntp
Version: 0.1.1
Summary: A Python package for interfacing with the Network Time Protocol
Home-page: http://github.com/werdl/libntp
License: Apache-2.0
Author: werdl
Author-email: werdl_is_cool@outlook.com
Requires-Python: >=3.6
Classifier: License :: OSI Approved :: Apache Software License
Classifier: Programming Language :: Python :: 3
Classifier: Programming Language :: Python :: 3.6
Classifier: Programming Language :: Python :: 3.7
Classifier: Programming Language :: Python :: 3.8
Classifier: Programming Language :: Python :: 3.9
Classifier: Programming Language :: Python :: 3.10
Classifier: Programming Language :: Python :: 3.11
Project-URL: Repository, http://github.com/werdl/libntp
